IFTTTtoDomoticzUsingPushover/__init__.py
IFTTTtoDomoticzUsingPushover-0.9.3.dist-info/METADATA
IFTTTtoDomoticzUsingPushover-0.9.3.dist-info/RECORD
IFTTTtoDomoticzUsingPushover-0.9.3.dist-info/WHEEL
IFTTTtoDomoticzUsingPushover-0.9.3.dist-info/top_level.txt
